social_media_card/__init__.py
social_media_card/html_template.py
social_media_card/image_manip.py
social_media_card/paths.py
social_media_card/py.typed
social_media_card/resources/example_banner.png
social_media_card/resources/example_image.jpg
social_media_card/resources/template.html
social_media_card-2.0.1.dist-info/METADATA
social_media_card-2.0.1.dist-info/WHEEL
social_media_card-2.0.1.dist-info/RECORD
