Metadata-Version: 2.1
Name: social-media-card
Version: 2.0.1
Summary: Create clickable images for social media
License: MIT
Author: Shay Hill
Author-email: shay_public@hotmail.com
Requires-Python: >=3.9,<4.0
Classifier: License :: OSI Approved :: MIT License
Classifier: Programming Language :: Python :: 3
Classifier: Programming Language :: Python :: 3.9
Classifier: Programming Language :: Python :: 3.10
Classifier: Programming Language :: Python :: 3.11
Requires-Dist: Pillow (>=9.5.0,<10.0.0)
